proto/__init__.py
proto/grpcintegration/ControlMessagesProto_pb2.py
proto/grpcintegration/ControlMessagesProto_pb2_grpc.py
proto/grpcintegration/EventNotificationProto_pb2.py
proto/grpcintegration/EventNotificationProto_pb2_grpc.py
proto/grpcintegration/ServicesProto_pb2.py
proto/grpcintegration/ServicesProto_pb2_grpc.py
proto/grpcintegration/StatusProto_pb2.py
proto/grpcintegration/StatusProto_pb2_grpc.py
proto/grpcintegration/__init__.py
proto/net/ConnectPointProto_pb2.py
proto/net/ConnectPointProto_pb2_grpc.py
proto/net/DeviceIdProto_pb2.py
proto/net/DeviceIdProto_pb2_grpc.py
proto/net/DeviceProto_pb2.py
proto/net/DeviceProto_pb2_grpc.py
proto/net/DisjointPathProto_pb2.py
proto/net/DisjointPathProto_pb2_grpc.py
proto/net/HostIdProto_pb2.py
proto/net/HostIdProto_pb2_grpc.py
proto/net/HostLocationProto_pb2.py
proto/net/HostLocationProto_pb2_grpc.py
proto/net/HostProto_pb2.py
proto/net/HostProto_pb2_grpc.py
proto/net/LinkProto_pb2.py
proto/net/LinkProto_pb2_grpc.py
proto/net/MastershipRoleProto_pb2.py
proto/net/MastershipRoleProto_pb2_grpc.py
proto/net/PathProto_pb2.py
proto/net/PathProto_pb2_grpc.py
proto/net/PortProto_pb2.py
proto/net/PortProto_pb2_grpc.py
proto/net/ProviderIdProto_pb2.py
proto/net/ProviderIdProto_pb2_grpc.py
proto/net/RegionProto_pb2.py
proto/net/RegionProto_pb2_grpc.py
proto/net/__init__.py
dnos-0.1.3.dist-info/LICENSE
dnos-0.1.3.dist-info/METADATA
dnos-0.1.3.dist-info/WHEEL
dnos-0.1.3.dist-info/top_level.txt
dnos-0.1.3.dist-info/RECORD
